datahunt
