Metadata-Version: 1.1
Name: datahunt
Version: 0.2.0
Summary: Python library for testing data science skills
Home-page: https://github.com/andreaschandra
Author: Andreas Chandra
Author-email: andreas@jakartaresearch.com
License: MIT
Keywords: data,sql,data-science,data-engineering
Platform: UNKNOWN
Classifier: Development Status :: 2 - Pre-Alpha
Classifier: Intended Audience :: Education
Classifier: License :: OSI Approved :: BSD License
Classifier: Operating System :: POSIX :: Linux
Classifier: Programming Language :: Python :: 3
Classifier: Programming Language :: Python :: 3.5
Classifier: Programming Language :: Python :: 3.6
Classifier: Programming Language :: Python :: 3.7
Classifier: Programming Language :: Python :: 3.8
Classifier: Programming Language :: Python :: 3.9
Classifier: Programming Language :: Python :: 3.10
Classifier: Programming Language :: Python :: 3.11
